[{"name":"Aatrox"},
{"name":"Ahri"},
{"name":"Akali"},
{"name":"Akshan"},
{"name":"Alistar"},
{"name":"Amumu"},
{"name":"Anivia"},
{"name":"Annie"},
{"name":"Aphelios"},
{"name":"Ashe"},
{"name":"AurelionSol"},
{"name":"Azir"},
{"name":"Bard"},
{"name":"Belveth"},
{"name":"Blitzcrank"},
{"name":"Brand"},
{"name":"Braum"},
{"name":"Caitlyn"},
{"name":"Camille"},
{"name":"Cassiopeia"},
{"name":"Chogath"},
{"name":"Corki"},
{"name":"Darius"},
{"name":"Diana"},
{"name":"Draven"},
{"name":"DrMundo"},
{"name":"Ekko"},
{"name":"Elise"},
{"name":"Evelynn"},
{"name":"Ezreal"},
{"name":"Fiddlesticks"},
{"name":"Fiora"},
{"name":"Fizz"},
{"name":"Galio"},
{"name":"Gangplank"},
{"name":"Garen"},
{"name":"Gnar"},
{"name":"Gragas"},
{"name":"Graves"},
{"name":"Gwen"},
{"name":"Hecarim"},
{"name":"Heimerdinger"},
{"name":"Illaoi"},
{"name":"Irelia"},
{"name":"Ivern"},
{"name":"Janna"},
{"name":"JarvanIV"},
{"name":"Jax"},
{"name":"Jayce"},
{"name":"Jhin"},
{"name":"Jinx"},
{"name":"Kaisa"},
{"name":"Kalista"},
{"name":"Karma"},
{"name":"Karthus"},
{"name":"Kassadin"},
{"name":"Katarina"},
{"name":"Kayle"},
{"name":"Kayn"},
{"name":"Kennen"},
{"name":"Khazix"},
{"name":"Kindred"},
{"name":"Kled"},
{"name":"KogMaw"},
{"name":"KSante"},
{"name":"Leblanc"},
{"name":"LeeSin"},
{"name":"Leona"},
{"name":"Lillia"},
{"name":"Lissandra"},
{"name":"Lucian"},
{"name":"Lulu"},
{"name":"Lux"},
{"name":"Malphite"},
{"name":"Malzahar"},
{"name":"Maokai"},
{"name":"MasterYi"},
{"name":"Milio"},
{"name":"MissFortune"},
{"name":"MonkeyKing"},
{"name":"Mordekaiser"},
{"name":"Morgana"},
{"name":"Naafiri"},
{"name":"Nami"},
{"name":"Nasus"},
{"name":"Nautilus"},
{"name":"Neeko"},
{"name":"Nidalee"},
{"name":"Nilah"},
{"name":"Nocturne"},
{"name":"Nunu"},
{"name":"Olaf"},
{"name":"Orianna"},
{"name":"Ornn"},
{"name":"Pantheon"},
{"name":"Poppy"},
{"name":"Pyke"},
{"name":"Qiyana"},
{"name":"Quinn"},
{"name":"Rakan"},
{"name":"Rammus"},
{"name":"RekSai"},
{"name":"Rell"},
{"name":"Renata"},
{"name":"Renekton"},
{"name":"Rengar"},
{"name":"Riven"},
{"name":"Rumble"},
{"name":"Ryze"},
{"name":"Samira"},
{"name":"Sejuani"},
{"name":"Senna"},
{"name":"Seraphine"},
{"name":"Sett"},
{"name":"Shaco"},
{"name":"Shen"},
{"name":"Shyvana"},
{"name":"Singed"},
{"name":"Sion"},
{"name":"Sivir"},
{"name":"Skarner"},
{"name":"Sona"},
{"name":"Soraka"},
{"name":"Swain"},
{"name":"Sylas"},
{"name":"Syndra"},
{"name":"TahmKench"},
{"name":"Taliyah"},
{"name":"Talon"},
{"name":"Taric"},
{"name":"Teemo"},
{"name":"Thresh"},
{"name":"Tristana"},
{"name":"Trundle"},
{"name":"Tryndamere"},
{"name":"TwistedFate"},
{"name":"Twitch"},
{"name":"Udyr"},
{"name":"Urgot"},
{"name":"Varus"},
{"name":"Vayne"},
{"name":"Veigar"},
{"name":"Velkoz"},
{"name":"Vex"},
{"name":"Vi"},
{"name":"Viego"},
{"name":"Viktor"},
{"name":"Vladimir"},
{"name":"Volibear"},
{"name":"Warwick"},
{"name":"Xayah"},
{"name":"Xerath"},
{"name":"XinZhao"},
{"name":"Yasuo"},
{"name":"Yone"},
{"name":"Yorick"},
{"name":"Yuumi"},
{"name":"Zac"},
{"name":"Zed"},
{"name":"Zeri"},
{"name":"Ziggs"},
{"name":"Zilean"},
{"name":"Zoe"},
{"name":"Zyra"}]